LICENSE
README.md
setup.py
aktime/TimeCalcu.py
aktime/__init__.py
aktime.egg-info/PKG-INFO
aktime.egg-info/SOURCES.txt
aktime.egg-info/dependency_links.txt
aktime.egg-info/requires.txt
aktime.egg-info/top_level.txt