Metadata-Version: 2.1
Name: aktime
Version: 0.1.5
Summary: Function time calculator
Home-page: https://github.com/AustinKuture/AKTime.git
Author: Kuture
Author-email: kuture@163.com
License: MIT Licence
Keywords: pip,aktime,TimeCalcu,timetool,kuture
Platform: any
License-File: LICENSE
